core/__init__.py
core/collective_mesh_runner.py
core/production_router_hardened.py
core/router_lite_engine.py
core/runtime_tiny_safe.py
dexa/__init__.py
dexa/bridge_log_viewer.py
dexa/bridge_route_validator.py
dexa/cli.py
dexa/dexa_agi_loop.py
dexa/dexa_mcp_bridge.py
dexa/dom_capture_launcher.py
dexa/dom_capture_smoke.py
dexa/excel_simulation.py
dexa/existential_reasoning_proxy.py
dexa/playwright_bridge_client.py
dexa/runtime_guard.py
dexa/setup_runtime.py
echo_engine/__init__.py
echo_engine/audit_api.py
echo_engine/audit_snapshot.py
echo_engine/demo_cpu_stable.py
echo_engine/enforcement.py
echo_engine/event_classifier.py
echo_engine/evidence_store.py
echo_engine/example_image_judgment.py
echo_engine/external_observation_layer.py
echo_engine/integrated_observation_judgment.py
echo_engine/intrusion_detector.py
echo_engine/judgment_layer.py
echo_engine/llm_router.py
echo_engine/pause_manager.py
echo_engine/phase1_runner.py
echo_engine/phase1_runner_n5.py
echo_engine/phase2_runner_constitution.py
echo_engine/process_fingers2.py
echo_engine/quick_test_tinyllama.py
echo_engine/real_image_finger_counter.py
echo_engine/reclassify_n5.py
echo_engine/reclassify_phase2_v3.py
echo_engine/reseed_hook.py
echo_engine/responsibility_guard.py
echo_engine/test_cpu_stable.py
echo_engine/test_integrated_judgment.py
echo_engine/test_judge_models.py
echo_engine/test_observation_judgment.py
echo_engine/two_stage_judgment_pipeline.py
echosystem/__init__.py
eui/debug_console_errors.py
eui/debug_runtime_tab.py
eui/open_eui_browser.py
eui/test_console_interaction.py
eui/test_eui_complete.py
eui/test_loop_integration.py
eui/test_teaching_loop.py
eui/test_vault_integration.py
eui/test_viewer_integration.py
ops/__init__.py
ops/echo_ops_dashboard.py
ops/metrics_agent.py
ops/slo_monitor.py
tools/__init__.py
tools/aoi_ingest.py
tools/aoi_simulation_export.py
tools/aoi_stage_inference.py
tools/aoi_training_export.py
tools/apple_watch_validation_runner.py
tools/challenge1_validation_runner.py
echo_aoi_pipeline-0.1.0.dist-info/METADATA
echo_aoi_pipeline-0.1.0.dist-info/WHEEL
echo_aoi_pipeline-0.1.0.dist-info/entry_points.txt
echo_aoi_pipeline-0.1.0.dist-info/top_level.txt
echo_aoi_pipeline-0.1.0.dist-info/RECORD
