Metadata-Version: 2.4
Name: echo-aoi-pipeline
Version: 0.1.0
Summary: Dexa CLI for Echo Judgment System
Author: Heo
Requires-Dist: pillow>=10.0.0
